{"Name": "HMS Calypso", "Builder": "Hawthorn Leslie and Company", "Laid down": "17 February 1916", "Launched": "24 January 1917", "Commissioned": "21 June 1917", "Fate": "Sunk 12 June 1940", "Class and type": "C-class light cruiser", "Displacement": "4,120 long tons (4,190 t)[1]", "Length": "450 ft (140 m)", "Beam": "42.9 ft (13.1 m)", "Draught": "14.3 ft (4.4 m)", "Installed power": "40,000 shp (30,000 kW)", "Propulsion": "2 \u00d7 Brown-Curtis geared steam turbines\n6 \u00d7 Yarrow boilers\n2 \u00d7 shafts", "Speed": "29 kn (33 mph; 54 km/h)", "Capacity": "Fuel oil: 300 short tons (270 t) (normal); 935 short tons (848 t) (maximum)", "Complement": "344", "Armament": "5 \u00d7 BL 6 in (150 mm) Mk XII guns, 2 \u00d7 QF 3 inch 20 cwt anti-aircraft guns, 4 \u00d7 QF 3-pounder guns, 1 \u00d7 machine gun, 8 \u00d7 21 inch (533 mm) torpedo tubes", "Armour": "Side: 3 in (7.6 cm) (amidships); 1.25\u20132.25 in (3.2\u20135.7 cm) (bow); 2\u20132.5 in (5.1\u20136.4 cm) (stern)\nDeck: 1 in (2.5 cm) (upper, amidships); 1 in (2.5 cm) (over rudder)"}