{"Name": "HMS Fidelity", "Builder": "H. & C. Grayson Ltd., Garston, Liverpool", "Completed": "1920", "Commissioned": "24 September 1940", "Fate": "Sunk, 30 December 1942", "Type": "Special Service Vessel", "Tonnage": "2,356 GRT", "Length": "80.7 m (264 ft 9 in)", "Beam": "12.6 m (41 ft 4 in)", "Depth": "5.7 m (18 ft 8 in)", "Propulsion": "252 nhp triple expansion steam engine", "Speed": "10.5 knots (19.4 km/h; 12.1 mph)", " craft carried": "1 \u00d7 Motor Torpedo Boat\n2 \u00d7 Landing Craft", "Complement": "280", "Armament": "4 \u00d7 4 in (100 mm) guns\n4 \u00d7 torpedo tubes", "Aircraft carried": "2 \u00d7 OS2U Kingfisher floatplanes"}