{"Name": "HMS Lamerton\nINS Gomati", "Ordered": "3 September 1939", "Builder": "Swan Hunter", "Laid down": "10 April 1940", "Launched": "14 December 1940", "Commissioned": "16 August 1941\n24 April 1953", "Identification": "pennant number: L88\npennant number: D93", "awards": "Atlantic, 1941\u201342\nArctic, 1942\nNorth Africa, 1942\u201343\nSicily, 1943\nSalerno, 1943\nMediterranean, 1944\nAegean, 1943\nAdriatic, 1944", "Fate": "Loaned, then sold, to Indian Navy\nScrapped", "Acquired": "April 1958", "Decommissioned": "1975", "Class and type": "Type II Hunt-class destroyer", "Displacement": "1,050 long tons (1,070 t) standard[1]\n1,430 long tons (1,450 t) full load", "Length": "85.3 m (279 ft 10 in) o/a", "Beam": "9.6 m (31 ft 6 in)", "Draught": "2.51 m (8 ft 3 in)", "Propulsion": "2 Admiralty 3-drum boilers\n2 shaft Parsons geared turbines, 19,000 shp[1]", "Speed": "27 knots (31 mph; 50 km/h)\n25.5 kn (29.3 mph; 47.2 km/h) full", "Range": "3,700 nmi (6,900 km) at 14 kn (26 km/h)[1]", "Complement": "164", "Armament": "6 \u00d7 QF 4 in Mark XVI guns on twin mounts Mk. XIX\n4 \u00d7 QF 2 pdr Mk. VIII on quad mount MK.VII\n2 (later 4) \u00d7 20 mm Oerlikons on single mounts P Mk. III\n[1]\n110 depth charges, 2 throwers, 3 racks"}