{"Name": "Crusader\nOttawa", "Ordered": "15 July 1930", "Builder": "Portsmouth Dockyard", "Laid down": "12 September 1930", "Launched": "30 September 1931", "Completed": "2 May 1932", "Identification": "Pennant number: H60", "Motto": "Non nobis Domine\n(\"Not under us, Lord\")", "Fate": "Transferred to the Royal Canadian Navy, 15 June 1938\nSunk by U-91, 14 September 1942", "Badge": "On a Field Black, a Shield silver, thereon a cross Red", "Namesake": "Ottawa River", "Commissioned": "15 June 1938", "awards": "Atlantic, 1939\u201345", "Class and type": "C-class destroyer", "Displacement": "1,375 long tons (1,397 t) (standard)\n1,865 long tons (1,895 t) (deep)", "Length": "329 ft (100.3 m) o/a", "Beam": "33 ft (10.1 m)", "Draught": "12 ft 6 in (3.8 m)", "Installed power": "36,000 shp (27,000 kW)", "Propulsion": "2 \u00d7 shafts\n2 \u00d7 Parsons geared steam turbines\n3 \u00d7 Admiralty 3-drum boilers", "Speed": "36 knots (67 km/h; 41 mph)", "Range": "5,500 nmi (10,200 km; 6,300 mi) at 15 knots (28 km/h; 17 mph)", "Complement": "145", "Armament": "4 \u00d7 1 \u2013 QF 4.7-inch Mk IX guns\n1 \u00d7 1 \u2013 QF 3-inch 20 cwt anti-aircraft gun\n2 \u00d7 1 \u2013 QF 2-pounder Mk II AA guns\n2 \u00d7 4 \u2013 21 inch (533 mm) torpedo tubes\n6 \u00d7 depth charges, 3 chutes"}