{"Name": "HMS Scourge\nHNLMS Evertsen", "Ordered": "9 January 1941", "Builder": "Cammell Laird, Birkenhead", "Laid down": "26 June 1941", "Launched": "8 December 1942", "Commissioned": "14 July 1943", "Out of service": "Sold to the Royal Netherlands Navy on 1 February 1946", "Identification": "Pennant number: G01\nD802", "awards": "Arctic 1943-45\nNormandy 1944", "Badge": "On a Field White. a cat-o-nine tails proper", "Acquired": "1 February 1946", "Fate": "Scrapped from July 1963", "Class and type": "S-class destroyer", "Displacement": "1,710 long tons (1,740 t) (standard)\n2,530 long tons (2,570 t) (deep load)", "Length": "362 ft 9 in (110.6 m) (o/a)", "Beam": "35 ft 9 in (10.9 m)", "Draught": "14 ft 6 in (4.4 m) (deep)", "Installed power": "40,000 shp (30,000 kW)\n2 \u00d7 Admiralty 3-drum boilers", "Propulsion": "2 \u00d7 shafts; 2 \u00d7 Parsons geared steam turbines", "Speed": "36 knots (67 km/h; 41 mph)", "Range": "4,675 nmi (8,658 km; 5,380 mi) at 20 knots (37 km/h; 23 mph)", " processing systems": "Radar Type 290 air warning\nRadar Type 285 ranging & bearing", "Armament": "4 \u00d7 single 4.7-inch (120 mm) Mark XII dual-purpose guns\n1 \u00d7 twin Bofors 40 mm AA guns\n4 \u00d7 twin QF 20 mm Oerlikon AA guns\n2 \u00d7 quadruple 21-inch torpedo tubes\n4 \u00d7 throwers and 2 \u00d7 racks for 70 depth charges"}