{"Name": "HMS Talybont", "Ordered": "23 August 1940", "Builder": "J. Samuel White, Cowes", "Laid down": "28 November 1941", "Launched": "3 February 1943", "Commissioned": "19 May 1943", "Identification": "pennant number: L18", "Fate": "Sold for scrap 1961", "Class and type": "Type III Hunt-class destroyer", "Displacement": "1,050 long tons (1,070 t) standard,\n1,490 long tons (1,510 t) full load", "Length": "264 ft 3 in (80.54 m) pp,\n280 ft (85.34 m) oa", "Beam": "31 ft 6 in (9.60 m)", "Draught": "7 ft 9 in (2.36 m)", "Propulsion": "2 Admiralty 3-drum boilers\n2 shaft Parsons geared turbines, 19,000 shp (14,000 kW)", "Speed": "27 kn (50 km/h; 31 mph)", "Range": "3,700 nmi (6,900 km; 4,300 mi) at 14 kn (26 km/h; 16 mph)", "Complement": "168", "Armament": "4 \u00d7 QF 4 in Mark XVI guns on twin mounts Mk. XIX\n5 \u00d7 QF 2 pdr Mk. VIII (1 \u00d7 quad mount and 1 \u00d7 single bow chaser mount)\n3 \u00d7 20 mm Oerlikons\n2 \u00d7 21 in (533 mm) torpedo tubes\n70 depth charges, 4 throwers, 2 racks"}