{"Class and type": "Merchant vessel\nTroop and DP transport\nCargo ship\nMerchant vessel", "Name": "Togo\nSchiff 14\nTogo\nSvalbard, then Tilthorn and Stella Marina\nTogo\nLacasielle, then Topeka", "Namesake": "Togo\nBattle of Coronel", "Operator": "Woermann Line\nKriegsmarine\nLuftwaffe\nDeutsch Afrikanische Schiffahrts GmbH, Hamburg", "Builder": "Bremer Vulkan, Vegesack\nWilton, Rotterdam", "Launched": "13 August 1938", "Homeport": "Hamburg\nKiel\nKiel", "Identification": "Code Letters DJXJ\n\nIMO number: 5363029", "Fate": "Requisitioned by Kriegsmarine, 1939\nTransferred to the Luftwaffe, 1943\nWar booty, 1945; transferred from UK to USA, then to Norway\nSold\nSold\n\nRan aground on 21 November 1984\nCoatzacoalcos, Mexico\n18\u00b010\u203212\u2033N 94\u00b018\u203236\u2033W\ufeff / \ufeff18.17000\u00b0N 94.31000\u00b0W\ufeff / 18.17000; -94.31000", "Yard number": "10", "Acquired": "Requisitioned, 1939\n1943\n14 March 1946\nNovember 1956\nMarch 1968", "Recommissioned": "December 1942\n1943", "Renamed": "(HSK Coronel, 1942)", "Reclassified": "Minelayer, 1940\nAuxiliary cruiser, 1942\nMinesweeper, 1943\n\nNight fighter guide ship, 1943", "Nickname(s)": "HSK-10\nRaider K", "Badge": "", "Type": "Night fighter guide ship", "Displacement": "12,700 t (12,500 long tons)[1]", "Length": "134 m (439 ft 8 in)", "Beam": "17.9 m (58 ft 9 in)", "Draft": "7.9 m (25 ft 11 in)", "Installed power": "5,100 hp (3,800 kW)", "Propulsion": "2 \u00d7 8-cylinder diesel engines\n1 \u00d7 shaft", "Speed": "16 kn (30 km/h; 18 mph)", "Endurance": "36,000 nmi (67,000 km; 41,000 mi) at 10 kn (19 km/h; 12 mph)[2]", "Complement": "283 crew plus 74 radar specialists from the Luftwaffe", " processing systems": "FuMG A1 Freya radar early warning radar\nW\u00fcrzburg-Riese gun-laying radar", "Armament": "3 \u00d7 10,5 cm anti-aircraft guns\n8 \u00d7 3,7 cm anti-aircraft guns (4 \u00d7 2)\n22 \u00d7 20 mm anti-aircraft cannons (5 \u00d7 4, 2 \u00d7 1)", "Aircraft carried": "She could guide two night fighters simultaneously"}