{"Name": "Nov\u00edk", "Builder": "Putilovsky Plant, St. Petersburg", "Laid down": "1 July 1910", "Launched": "4 July 1911", "Commissioned": "9 September 1913", "Fate": "Joined the Bolsheviks, November 1917", "Type": "Destroyer", "Displacement": "1,260 tonnes (1,240 long tons) (normal)\n1,590 tonnes (1,560 long tons)", "Length": "102.4 m (335 ft 11 in)", "Beam": "9.5 m (31 ft 2 in)", "Draught": "7.2 m (23 ft 7 in)", "Installed power": "6 water-tube boilers\n39,000 shp (29,000 kW)", "Propulsion": "3 shafts, steam turbines", "Speed": "37.3 knots (69.1 km/h; 42.9 mph) (trials)", "Range": "2,000 nmi (3,700 km) at 21 knots (39 km/h; 24 mph)", "Complement": "142 men", "Armament": "4 \u00d7 single 102 mm (4.0 in) guns\n4 \u00d7 twin 457 mm (18.0 in) torpedo tubes\n60 mines"}